COPYING
MANIFEST.in
README.rst
buildout.cfg
requirements.txt
setup.py
version.txt
bob/__init__.py
bob.db.siw.egg-info/PKG-INFO
bob.db.siw.egg-info/SOURCES.txt
bob.db.siw.egg-info/dependency_links.txt
bob.db.siw.egg-info/entry_points.txt
bob.db.siw.egg-info/requires.txt
bob.db.siw.egg-info/top_level.txt
bob/db/__init__.py
bob/db/siw/__init__.py
bob/db/siw/common.py
bob/db/siw/config.py
bob/db/siw/driver.py
bob/db/siw/query.py
bob/db/siw/test.py
bob/db/siw/lists/dev_files.lst
bob/db/siw/lists/eval_files.lst
bob/db/siw/lists/train_files.lst
bob/db/siw/lists/Protocol_1/dev/for_attack.lst
bob/db/siw/lists/Protocol_1/dev/for_real.lst
bob/db/siw/lists/Protocol_1/eval/for_attack.lst
bob/db/siw/lists/Protocol_1/eval/for_real.lst
bob/db/siw/lists/Protocol_1/train/for_attack.lst
bob/db/siw/lists/Protocol_1/train/for_real.lst
bob/db/siw/lists/Protocol_2_1/dev/for_attack.lst
bob/db/siw/lists/Protocol_2_1/dev/for_real.lst
bob/db/siw/lists/Protocol_2_1/eval/for_attack.lst
bob/db/siw/lists/Protocol_2_1/eval/for_real.lst
bob/db/siw/lists/Protocol_2_1/train/for_attack.lst
bob/db/siw/lists/Protocol_2_1/train/for_real.lst
bob/db/siw/lists/Protocol_2_2/dev/for_attack.lst
bob/db/siw/lists/Protocol_2_2/dev/for_real.lst
bob/db/siw/lists/Protocol_2_2/eval/for_attack.lst
bob/db/siw/lists/Protocol_2_2/eval/for_real.lst
bob/db/siw/lists/Protocol_2_2/train/for_attack.lst
bob/db/siw/lists/Protocol_2_2/train/for_real.lst
bob/db/siw/lists/Protocol_2_3/dev/for_attack.lst
bob/db/siw/lists/Protocol_2_3/dev/for_real.lst
bob/db/siw/lists/Protocol_2_3/eval/for_attack.lst
bob/db/siw/lists/Protocol_2_3/eval/for_real.lst
bob/db/siw/lists/Protocol_2_3/train/for_attack.lst
bob/db/siw/lists/Protocol_2_3/train/for_real.lst
bob/db/siw/lists/Protocol_2_4/dev/for_attack.lst
bob/db/siw/lists/Protocol_2_4/dev/for_real.lst
bob/db/siw/lists/Protocol_2_4/eval/for_attack.lst
bob/db/siw/lists/Protocol_2_4/eval/for_real.lst
bob/db/siw/lists/Protocol_2_4/train/for_attack.lst
bob/db/siw/lists/Protocol_2_4/train/for_real.lst
bob/db/siw/lists/Protocol_3_1/dev/for_attack.lst
bob/db/siw/lists/Protocol_3_1/dev/for_real.lst
bob/db/siw/lists/Protocol_3_1/eval/for_attack.lst
bob/db/siw/lists/Protocol_3_1/eval/for_real.lst
